browser_service/__init__.py
browser_service/config.py
browser_service/agent/__init__.py
browser_service/agent/actions.py
browser_service/agent/registration.py
browser_service/api/__init__.py
browser_service/api/handlers.py
browser_service/api/routes.py
browser_service/browser/__init__.py
browser_service/browser/cleanup.py
browser_service/browser/session.py
browser_service/locators/__init__.py
browser_service/locators/extraction.py
browser_service/locators/generation.py
browser_service/locators/smart_locator.py
browser_service/locators/validation.py
browser_service/prompts/__init__.py
browser_service/prompts/system.py
browser_service/prompts/templates.py
browser_service/prompts/workflow.py
browser_service/tasks/__init__.py
browser_service/tasks/processor.py
browser_service/tasks/workflow.py
browser_service/utils/__init__.py
browser_service/utils/json_parser.py
browser_service/utils/logging_setup.py
browser_service/utils/metrics.py
browser_service-1.0.17.dist-info/licenses/LICENSE
browser_service-1.0.17.dist-info/METADATA
browser_service-1.0.17.dist-info/WHEEL
browser_service-1.0.17.dist-info/top_level.txt
browser_service-1.0.17.dist-info/RECORD
